{"bilingual language arts sixth grade teacher": "Bilingual Language Arts Teacher", "mortgage banking default operations specialist ii": "Mortgage Banking Operations Specialist", "operations manager": "Operations Manager", "president/chief executive officer": "Chief Executive Officer", "assistant banking center manager": "Banking Center Manager", "accountant": "Accountant", "bilingual domestic violence advocate": "Bilingual Advocate", "preventative healthcare intern": "Preventative Healthcare Intern", "finance director and treasurer": "Finance Director", "personal trainer, group fitness instructor": "Fitness Instructor", "principal accountant": "Principal Accountant", "banking relationship specialist": "Banking Specialist", "project manager": "Project Manager", "hospital & physician billing specialist": "Medical Billing Specialist", "college assistant": null, "senior vp - information technology": "Director/VP of Information Technology", "hr assistant": "Human Resources Specialist", "asp.net web developer": null, "lead administrator": "Administrator", "territory hr manager": "Regional HR Manager", "partner account manager": "Key Account Manager", "aviation supply technician": "Aviation Technician", "k-12 principal": "Principal", "vice president": "Vice President", "volunteer advocate": null, "account receivable": null, "healthcare recruiter": "Healthcare Recruiter", "professional healthcare representative": "Healthcare Representative", "senior hr manager": "HR Director", "domestic violence and sexual assault advocate": "Domestic Violence and Sexual Assault Advocate", "hr consulting": "HR Consultant", "internship": "Intern", "floater/teacher": null, "secretary - finance division": null, "gunnery sergeant": "Gunnery Sergeant", "creative director": "Creative Director", "licensed united healthcare insurance sales agent": "Licensed Insurance Agent", "cna in skilled healthcare": null, "director of applications": "Director of Applications", "michael's arts and crafts store": null, "sale consultant": "Senior Sales Consultant", "talented arts program instructional coordinator": "Program Coordinator", "customer service advocate ii": "Customer Service Advocate", "visual arts teacher": "Visual Arts Teacher", "phlebotomist": null, "banking": null, "family and community advocate": "Advocate", "senior specialty sales representative": "Senior Specialty Sales Representative", "certified custom framer": "Certified Custom Framer", "retail banking director": "Retail Banking Director", "instructional coach": "Instructional Coach", "information technology manager / network engineer": "Information Technology Manager", "senior member advocate": "Senior Member Advocate", "warehouse lead": "Warehouse Lead", "english language arts teacher": "English Language Arts Teacher", "finance coordinator": "Finance Manager", "benefit advocate supervisor": "Benefit Advocate", "sales & service associate": "Sales Associate", "support & network services intern": null, "driver": null, "tutoring consultant": "Tutoring Consultant", "senior lending officer - vp executive officer": "Senior Lending Officer", "global finance accountant": "Global Finance Accountant", "postal support employee": null, "vice president-business banking sales manager and healthcare specialty banker": "Vice President", "finance business partner": "Finance Business Partner", "operations research analyst": "Operations Research Analyst", "guest lecturer": "Guest Lecturer", "aviation safety assistant": "Aviation Safety Assistant", "software quality assurance analyst ii": "Software Quality Assurance Analyst", "government relations, communications and organizational development director": null, "hr generalist/recruiter": "HR Generalist", "software engineer": "Software Engineer", "vzw customer tech advocate": "Customer Advocate", "program administrator": "Program Administrator", "assistant director": "Assistant Director", "director of theater": "Director of Theater", "hr associate mobilization coordinator": null, "healthcare consultant": "Principal Consultant", "hr business partner": "HR Business Partner", "programme finance associate": "Programme Finance Associate", "information technology certified technician": "Information Technology Technician", "advocate": "Advocate", "sous chef/line cook": "Sous Chef", "library educational aide": null, "unmanned aviation technician supervisor": "Unmanned Aviation Technician Supervisor", "student teacher": "NULL", "avid tutor": null, "field project supervisor": "Field Project Supervisor", "training manager": "Training Manager", "pa media group": null, "impact": null, "adjunct faculty, zanvyl kreiger school of arts and sciences, advanced academic programs": "Adjunct Faculty", "practice manager": "Practice Manager", "electronic health record optimization specialist": null, "manager, continuous improvement": "Manager", "summer camp counselor": null, "corporate banking assistant, intern": "NULL", "administrative assistant director human resources manager production manager engineering": null, "customer service representative": "Customer Service Representative", "information technology intern (test automation engineer)": "Information Technology Intern", "international certification program management": null, "supervisor, accountant": "Supervisor", "marketing manager": "Marketing Manager", "owner/operator": "Owner", "investment banking summer analyst": "Analyst", "line attendant": "Attendant", "faculty, clinical instructor, & clinical coordinator": null, "professional summary": null, "dance instructor": "Dance Instructor", "lead information technology support specialist": "Information Technology Specialist", "platform architect, healthcare incubation lab (hil)": null, "fitness trainee/recreation management intern": "Recreation Coordinator", "subject matter expert (information technology assistant)": "Subject Matter Expert", "packaging buyer/research and development lead": null, "corporate controller": "Corporate Controller", "volunteer hr -ivolunteer": null, "rn / asst. head nurse practice leader": "Assistant Head Nurse", "director, compounding sales specialist": "Director", "adventure run coordinator": "Adventure Run Coordinator", "landscape technician": "Landscape Technician", "administrator of information technology": "Information Technology Manager", "health systems analyst": "Health Systems Analyst", "bank operations analyst": "Bank Operations Analyst", "health coach": "Health Coach", "working rf systems engineer": null, "advisor": "advisor", "placement agent / dorado beach resort": null, "personnel security specialist": "Personnel Security Specialist", "budget finance specialist senior": "Senior Budget Finance Specialist", "enumerator": "Enumerator", "yoga instructor": "Yoga Instructor", "server": null, "superintendent ii": "Superintendent", "community relations advocate supervisor": "Community Relations Advocate Supervisor", "claims service specialist": "Claims Service Specialist", "senior director of business operations - healthcare": "Senior Director of Business Operations", "manager, digital marketing and communications": "Manager", "senior student accounts officer": "Senior Student Accounts Officer", "system administrator/assistant supervisor": "System Administrator", "clinical research coordinator mentor - quality assurance": null, "senior commercial business banking relationship manager, vp": "Senior Commercial Business Banking Relationship Manager", "senior supply sergeant": "senior supply sergeant", "ph inpatient/financial advocate supervisor": "Supervisor", "senior network security engineer": "Senior Network Security Engineer", "center director/head start family advocate": "Center Director", "managed pressure drilling field supervisor": "Managed Pressure Drilling Field Supervisor", "marketing and corporate communications merchant services transition communications project": null, "coordinator, donor relations": null, "soho properties, summer analyst": null, "information technology provisioning technician": null, "cashier": null, "maintenance mechanic": "Maintenance Mechanic", "inside sales representative": "Inside Sales Representative", "aviation executive officer": "Aviation Executive", "customer service rep 1 lead quality assurance coach account relationship specialist online": null, "co- founder/therapist and teaching artist": null, "executive assistant/office manager": "Office Manager", "program manager financial manager, facilities manager": null, "registered nurse clinical care coordinator- first aid": "Registered Nurse", "certified nurse assistant": "Nurse", "kids club attendant": null, "project coordinator associate": null, "revenue cycle advocate": null, "senior investment banking sales analyst": "Investment Banking Sales Analyst", "volunteer": null, "case manager/outreach advocate": "Case Manager", "healthcare associate": "Healthcare Associate", "recruiter-in-charge": "Recruiter-in-Charge", "field support specilist": null, "christopher townes": null, "air freight agent": null, "account executive": "Account Executive", "lead engineer - fluid systems and thermal accessories": "Lead Engineer", "branch manager": "Manager", "material control specialist": "Material Control Specialist", "clinical service advocate": "Clinical Service Advocate", "non commissioned security officer": null, "storekeeper ii": "Storekeeper", "fitness staff": "Fitness Director", "mechanical design engineer intern": null, "assistant, acquisitions and dispositions": null, "aviation maintenance egress leading petty officer leading petty officer": null, "managing principal": "Managing Principal", "nc air guard health services manager": null, "regional banking district manager vice president": "Regional Banking District Manager", "information technology bureau deputy director": "Deputy Director", "physical therapy aide": null, "director, vendor services and compliance": "Director of Vendor Services", "grants manager": "Grants Manager", "budget and administration manager": "Budget and Administration Manager", "substitute teacher": "Substitute Teacher", "flight manager": "flight manager", "combat marksmanship trainer/ primary marksmanship instructor": "Combat Marksmanship Trainer/Primary Marksmanship Instructor", "admissions executive": "Admissions Executive", "occupational health nurse coordinator": "Occupational Health Nurse Coordinator", "mechanical engineer": null, "aircraft sales": null, "head, information technology and information center": "Head of Information Technology", "director of national sales- us. healthcare": "Director of Sales, Healthcare", "hr - shared services supervisor": "HR Shared Services Supervisor", "highly accomplished healthcare analyst": "Highly Accomplished Healthcare Analyst", "lean six sigma black belt": "Lean Six Sigma Black Belt", "graduate engineer": "Graduate Engineer", "patient care technician": null, "pharmaceutical sales representative, women's healthcare specialist": null, "healthcare effectiveness and information set coordinator (hedis)": "Healthcare Coordinator", "client relations advocate": "Client Relations Advocate", "financial analyst intern": null, "admin operating room administrative coordinator": null, "amc computer specialist and intern": null, "financial consultant": "Financial Consultant", "experienced information technology manager": "Experienced Information Technology Manager", "receiving manager": "Receiving Manager", "production associate": "Production Associate", "karla lee": null, "hr benefits/leave coordinator": null, "business process analyst": "Business Process Analyst", "trip coordinator": "Trip Coordinator", "branch banker iii": "Branch Banker", "consumer banking default management supervisor": "Consumer Banking Default Management Supervisor", "regional recruiter": "Regional Recruiter", "teacher assistant": "Assistant", "healthcare clinical analyst": "Clinical Analyst", "senior advisor and national fundraising director": "Senior Advisor", "manager field": null, "passenger service concourse manager": "Passenger Services Manager", "banking boot camp participant": null, "information technology support specialistnetwork specialist pc technician it consultant": "Information Technology Consultant", "school counselor": "School Counselor", "management and program analysis": null, "child performer welfare advocate": "Child Performer Advocate", "express scripts": null, "plant fulfillment leader": "Plant Leader", "afscme union president": "union president", "child center asst dept head": null, "online learning coordinator - program training and support": "Learning Coordinator", "online coaching, personal training": null, "database programmer/analyst (.net developer)": null, "business analyst sr. technical business analyst": "Business Analyst", "healthcare instructional assistant": "Instructional Assistant", "information technology consultant, managing member": "Consultant", "eighth, ninth and tenth english teacher": null, "operations technician 1": null, "student": null, "school success advocate": "Advocate", "organizer and capacity building strategist": "Strategist", "occupational therapist": "Therapist", "rachael lobdell": null, "school library media specialist": "Librarian", "home healthcare technician": "healthcare technician", "general business management": "General Manager", "4/5 grade teacher": null, "licensed practical nurse- step-down unit": null, "game design intern": null, "aircraft hydraulics journyman": null, "business systems analyst i": "Business Systems Analyst", "sleep technologist, rpsgt": null, "overnight pharmacy technician": "pharmacy technician", "aviation parts salesman": "Sales Representative", "production excellence specialist": "production specialist", "national sales manager": "Senior Manager", "athletic director, coach, pe teacher": "Physical Education Director", "surgical clinical reviewer": "Surgical Clinical Reviewer", "transitional housing advocate": "Advocate", "sales & trading intern": null, "specialist of infantry": null, "dining services coordinator": "Dining Services Coordinator", "entrepreneur general manager": "General Manager", "trade finance officer": "Trade Finance Officer", "registered client service associate": "Client Service Associate", "force analyst": "senior analyst", "communicable disease specialist": "specialist", "field based nurse chart reviewer - healthcare informatics": null, "shift supervisor": "Supervisor", "healthcare administration intern": "Administration Intern", "interim membership director": "Director", "avp, finance": "Assistant Vice President", "health information specialist": "Health Information Specialist", "geek squad agent": "Agent", "assistant boy's basketball coach": null, "special finance manager": "special finance manager", "mover": null, "aviation camp assistant": null, "outside machinist": null, "equipment operator and fitness leader": null, "contracts and finance officer": "Financial Officer", "assistant to managing director": "Assistant Manager", "receptionist and veterinary technician": null, "aviation records analyst": "Senior Analyst", "healthcare": null, "senior analyst - business intelligence and analytics - healthcare": "Senior Analyst", "lead teller": "lead", "social media producer": "Social Media Professional", "human resource/ finance analyst": null, "director, quality improvement network facilitation": "Director", "purchasing agent": "Purchasing Coordinator", "phd candidate in finance": "Researcher", "care coordinator": "Care Coordinator", "direct client coordinator- counselor/ victim advocate": null, "patient health advocate": "Healthcare Professional", "security baggage handler/personnel screener": null, "am- replenishment stocker": null, "emergency room admitting specialist/quality assurance": "Admitting Specialist", "information technology": "Information Technology Specialist", "mds coordinator": "coordinator", "advanced level wheeled vehicle mechanic": "senior mechanic", "front desk attendant": null, "accommodation service executive ll": "Executive", "staff pharmacist": "Pharmacist", "manager of golf operations": "operations manager", "student finance consultant": "Financial Consultant", "svp, regional sales director wealth management": "Senior Vice President", "epic information technology specialist": "Epic Specialist", "teradata senior associate consultant": "senior consultant", "assistant information technology (it) director": "IT Director", "pest control tech": null, "fulfillment advocate": "Advocate", "membership coordinator": "Membership Coordinator", "audio/visual technician": null, "arts education intern": null, "gradation candidate advocate": null, "product specialist": "Product Specialist", "lead pharmacy technician advocate - supervisor": "Supervisor", "video director, east coast video for enterprise brands": "Video Director", "sales / finance manager": "Manager", "quality control inspector": "Quality Assurance Manager", "concierge/doorman": "Concierge", "donor advocate": "Advocate", "registered nurse, supervisor": "Supervisor", "legal specialist iii - investment banking subpoena compliance": null, "financial institutions examiner": "senior examiner", "volunteer accountant": null, "qa test analyst": "QA Test Analyst", "quality analyst/senior record keeping specialist": "Quality Analyst", "management consultant": "Management Consultant", "global it project manager": "global it project manager", "laborer": null, "assembly mechanic": "senior mechanic", "director of community": "Director of Community", "medical scribe": "Medical Scribe", "acting grade 4 customer/brand": null, "information technology specialist gs11": "Information Technology Specialist", "hr specialist/ horizontal engineer": "HR Specialist", "planner/scheduler": "Scheduler", "healthcare administrator/operational and staff reorg": null, "advocare distributor": "Distributor", "medical record technician": "Medical Record Specialist", "supervisory logistics management specialist": "Logistics Manager", "finance customer care rep lead": "Lead", "procurement analyst": "Procurement Specialist", "customer service representactive": null, "marketing & sales analyst": null, "electrical engineer": "Electrical Specialist", "hr volunteer asst. manager": null, "research assistant": "assistant", "software engineering co-op": null, "financial aid specialist": "Financial Specialist", "senior implementation manager": "senior implementation manager", "charge nurse": "charge nurse", "assistant football coach": "Head Coach", "medical support assistant (oa) gs-5 step 2": "Medical Support Assistant", "intervention specialist teacher of math and language arts": "Teacher", "night service representative": "Customer Service Representative", "network administrator": "Network Administrator", "dental hygienist": "Dental Hygienist", "branch chief information technology specialist": "Chief Information Technology Specialist", "lead operations engineer - global hawk project": "Lead Operations Engineer", "information technology specialist information security officer": "Information Security Specialist", "healthcare documentation services delivery manager": "Delivery Manager", "freelance it consultant": "Consultant", "commission specialist": "commission specialist", "field nurse": "nurse", "director of programming arts": "Director of Programming Arts", "court appointed special advocate": "Court Advocate", "night warehouse selector": "Warehouse Supervisor", "desktop support engineer": "IT Support Specialist", "administrative assistant/site clerk": "Administrative Assistant", "senior analyst data quality & governance": "senior analyst", "bakery entrepreneur": null, "staffing coordinator": "staffing coordinator", "child advocate manager": "Manager", "corporate facilitator, performance coach and developer": "Lead Coach", "patient experience manager": "Manager", "audit and recovery specialist": "Audit Specialist", "quality assurance advocate": "Quality Assurance Specialist", "practicum experience": null, "instructor/writer": null, "teller 3": null, "line service technician": "Technician", "corporate administrator": "Corporate Administrator", "v/p commercial relationship manager": "Vice President", "team member / pricer": null, "merchant services advocate": "merchant services advocate", "certified master personal trainer": "Master Trainer", "relationship support officer": "Relationship Manager", "radiological control technician": "Radiological Control Technician", "senior compliance officer": "senior compliance officer", "senior marketing automation consultant": "Senior Marketing Automation Consultant", "paralegal": "Paralegal", "revolving credit support specialist": "Specialist", "personal banker(safe)1 and business advocate": null, "material and tooling control lead": "Lead", "coordinator of student personnel services": "Coordinator of Student Services", "hr administrator/marketing associate hr administrator": null, "director, clinical research operations & medical science liaison": "Director", "lead aerospace assembler": "lead aerospace assembler", "aviation fuel quality control specialist": "Quality Control Specialist", "plant operator": null, "culinary arts instructor": "instructor", "dealership finance manager": "finance manager", "information technology and aws admin intern": null}